{
  "basics": {
    "name": "Justin Golden",
    "label": "Student",
    "picture": "",
    "email": "justingolden@rgbstudios.org",
    "phone": "310-425-5338",
    "website": "https://justingolden21.github.io",
    "summary": "I am studying for a B.S. in Computer Science at San Diego State University. I expect to graduate in Spring, 2020.",
    "location": {
      "address": "",
      "postalCode": "",
      "city": "San Diego",
      "countryCode": "USA",
      "region": "California"
    },
    "profiles": [
      {
        "network": "github",
        "username": "justingolden21",
        "url": "http://github.com/justingolden21"
      },
      {
        "network": "linkedin",
        "username": "justingolden21",
        "url": "http://linkedin.com/in/justingolden21"
      },
      {
        "network": "twitter",
        "username": "justingolden21",
        "url": "http://twitter.com/justingolden21"
      }
    ]
  },
  "interests": [
    {
      "name": "web development",
      "keywords": [
        "website",
        "webpage",
        "front end",
        "back end",
        "full stack",
        "web app"
      ]
    },
    {
      "name": "android development",
      "keywords": [
        "mobile",
        "apps"
      ]
    },
    {
      "name": "graphic design",
      "keywords": [
        "design",
        "graphic",
        "digital design",
        "icon",
        "logo"
      ]
    },
    {
      "name": "artificial intelligence",
      "keywords": [
        "machine learning",
        "bot",
        "chatbot"
      ]
    }
  ],
  "skills": [
    {
      "name": "Languages and Frameworks",
      "level": "",
      "keywords": [
        "Javascript",
        "HTML",
        "CSS",
        "Bootstrap",
        "Semantic UI",
        "Angular",
        "Sass",
        "Json",
        "XML",
        "Java",
        "C++",
        "C#",
        "Kotlin",
        "Python",
        "SQL"
      ]
    },
    {
      "name": "Toolsets/OS",
      "level": "",
      "keywords": [
        "Windows",
        "Git/GitHub",
        "Google Docs",
        "Google Sheets",
        "Google Slides",
        "Microsoft Word",
        "Microsoft Powerpoint",
        "Microsoft Excel",
        "Adobe Photoshop",
        "Adobe Illustrator",
        "Adobe Premiere Pro"
      ]
    }
  ],
  "education": [
    {
      "institution": "San Diego State University, San Diego, CA",
      "area": "Computer Science (expected Spring, 2020)",
      "studyType": "B.S.",
      "startDate": "2015",
      "endDate": "Present",
      "gpa": "",
      "courses": [
        "Machine Organization and Assembly Language", 
        "Data Structures",
        "Programming Languages",
        "Computer Architecture", 
        "Discrete Math", 
        "Linear Algebra",
        "Computer Science Ethics",
        "Systems Programming",
        "Algorithms and their Analysis",
      ]
    }
  ],
  "work": [
    {
      "company": "RGB Studios",
      "position": "President, Web Developer",
      "website": "rgbstudios.org",
      "startDate": "2015",
      "endDate": "Present",
      "summary": "Head of online presence and development of website, web apps, and android apps",
      "highlights": [
        "Maintain and update website, web apps, and android apps",
        "Provide support and listen to feedbac of users",
        "Design pixel and vector, graphics, and video editing"
      ]
    }
  ],
  "awards": [
    {
      "title": "AGL Game Jam 2018 Participant",
      "date": "2018",
      "awarder": "Aztec Game Lab",
      "summary": "participated in a game jam team to develop a complete game in unity in under 48 hours"
    }
  ]
}
